hipcat/__init__.py
hipcat/cli.py
hipcat-0.1.0.dist-info/DESCRIPTION.rst
hipcat-0.1.0.dist-info/METADATA
hipcat-0.1.0.dist-info/RECORD
hipcat-0.1.0.dist-info/WHEEL
hipcat-0.1.0.dist-info/entry_points.txt
hipcat-0.1.0.dist-info/metadata.json
hipcat-0.1.0.dist-info/top_level.txt
