Metadata-Version: 2.0
Name: hipcat
Version: 0.1.0
Summary: Pipe text to HipChat
Home-page: https://www.github.com/judy2k/hipcat/
Author: Mark Smith
Author-email: judy@judy.co.uk
License: GNU General Public License v2 (GPLv2)
Platform: any
Classifier: Development Status :: 3 - Alpha
Classifier: Environment :: Console
Classifier: License :: OSI Approved :: GNU General Public License v2 (GPLv2)
Classifier: Operating System :: OS Independent
Classifier: Programming Language :: Python
Classifier: Programming Language :: Python :: 3
Classifier: Programming Language :: Python :: 3.3
Classifier: Programming Language :: Python :: 3.4
Classifier: Programming Language :: Python :: 3.5
Classifier: Topic :: Communications :: Chat
Requires-Dist: click (>=4.0)
Requires-Dist: requests
